MeCab/_MeCab.cpython-311-aarch64-linux-gnu.so
MeCab/__init__.py
MeCab/cli.py
mecab_python3.libs/libmecab-608f3a6a.so.2.0.0
mecab_python3-1.0.10.dist-info/top_level.txt
mecab_python3-1.0.10.dist-info/RECORD
mecab_python3-1.0.10.dist-info/entry_points.txt
mecab_python3-1.0.10.dist-info/AUTHORS
mecab_python3-1.0.10.dist-info/METADATA
mecab_python3-1.0.10.dist-info/COPYING
mecab_python3-1.0.10.dist-info/WHEEL
