Metadata-Version: 2.1
Name: mecab-python3
Version: 1.0.10
Summary: Python wrapper for the MeCab morphological analyzer for Japanese
Home-page: https://github.com/SamuraiT/mecab-python3
Maintainer: Paul O'Leary McCann
Maintainer-email: polm@dampfkraft.com
License: BSD
Platform: UNKNOWN
Classifier: Development Status :: 6 - Mature
Classifier: Programming Language :: Python :: 3
Classifier: Programming Language :: Python :: 3.8
Classifier: Programming Language :: Python :: 3.9
Classifier: Programming Language :: Python :: 3.10
Classifier: Programming Language :: Python :: 3.11
Classifier: Programming Language :: Python :: 3.12
Classifier: Programming Language :: Python :: 3.13
Classifier: Intended Audience :: Developers
Classifier: Intended Audience :: Science/Research
Classifier: Natural Language :: Japanese
Classifier: Topic :: Software Development :: Libraries :: Python Modules
Classifier: Topic :: Text Processing :: Linguistic
Classifier: License :: OSI Approved :: BSD License
License-File: COPYING
License-File: AUTHORS
Provides-Extra: unidic
Requires-Dist: unidic ; extra == 'unidic'
Provides-Extra: unidic-lite
Requires-Dist: unidic-lite ; extra == 'unidic-lite'
